.coveragerc
.editorconfig
.gitattributes
.gitignore
CHANGES.rst
MANIFEST.in
README.rst
bootstrap-buildout.py
buildout.cfg
setup.py
collective/__init__.py
collective.dualresources.egg-info/PKG-INFO
collective.dualresources.egg-info/SOURCES.txt
collective.dualresources.egg-info/dependency_links.txt
collective.dualresources.egg-info/entry_points.txt
collective.dualresources.egg-info/namespace_packages.txt
collective.dualresources.egg-info/not-zip-safe
collective.dualresources.egg-info/requires.txt
collective.dualresources.egg-info/top_level.txt
collective/dualresources/__init__.py
collective/dualresources/configure.zcml
collective/dualresources/meta.zcml
collective/dualresources/testing.py
collective/dualresources/zcml.py
collective/dualresources/tests/__init__.py
collective/dualresources/tests/test_setup.py
docs/LICENSE.GPL
docs/LICENSE.rst
docs/index.rst