Metadata-Version: 1.1
Name: collective.dualresources
Version: 0.2
Summary: An extension of the plone.resource plone:static zcml directive, that allows to specify two folders for a resource directory registration: A dev-directory and a dist-directory. When plone is running in debug mode the filesystem path specified in dev-directory is used to serve static resources for this resource registration. The dist-directory is used when not in debug mode. This allows to use tools like grunt to build production versions of resources, including minification, concatenatio
Home-page: https://github.com/collective/dualresources
Author: Sune Broendum Woeller
Author-email: sune@woeller.dk
License: GPL
Keywords: Python Plone
Platform: UNKNOWN
Classifier: Environment :: Web Environment
Classifier: Framework :: Plone
Classifier: Programming Language :: Python
Classifier: Programming Language :: Python :: 2.7
